{
  "name": "genji",
  "rules": {
    "source_file": {
      "type": "REPEAT1",
      "content": {
        "type": "SEQ",
        "members": [
          {
            "type": "SYMBOL",
            "name": "_stmt"
          },
          {
            "type": "STRING",
            "value": ";"
          }
        ]
      }
    },
    "_stmt": {
      "type": "CHOICE",
      "members": [
        {
          "type": "SYMBOL",
          "name": "alter_stmt"
        },
        {
          "type": "SYMBOL",
          "name": "begin_stmt"
        },
        {
          "type": "SYMBOL",
          "name": "commit_stmt"
        },
        {
          "type": "SYMBOL",
          "name": "select_stmt"
        },
        {
          "type": "SYMBOL",
          "name": "delete_stmt"
        },
        {
          "type": "SYMBOL",
          "name": "update_stmt"
        },
        {
          "type": "SYMBOL",
          "name": "insert_stmt"
        },
        {
          "type": "SYMBOL",
          "name": "create_stmt"
        },
        {
          "type": "SYMBOL",
          "name": "drop_stmt"
        },
        {
          "type": "SYMBOL",
          "name": "rollback_stmt"
        },
        {
          "type": "SYMBOL",
          "name": "reindex_stmt"
        }
      ]
    },
    "alter_stmt": {
      "type": "SEQ",
      "members": [
        {
          "type": "STRING",
          "value": "ALTER"
        },
        {
          "type": "STRING",
          "value": "TABLE"
        },
        {
          "type": "SYMBOL",
          "name": "ident"
        },
        {
          "type": "CHOICE",
          "members": [
            {
              "type": "STRING",
              "value": "RENAME"
            },
            {
              "type": "STRING",
              "value": "ADD"
            }
          ]
        }
      ]
    },
    "begin_stmt": {
      "type": "SEQ",
      "members": [
        {
          "type": "STRING",
          "value": "BEGIN"
        },
        {
          "type": "CHOICE",
          "members": [
            {
              "type": "STRING",
              "value": "TRANSACTION"
            },
            {
              "type": "BLANK"
            }
          ]
        },
        {
          "type": "CHOICE",
          "members": [
            {
              "type": "SEQ",
              "members": [
                {
                  "type": "STRING",
                  "value": "READ"
                },
                {
                  "type": "CHOICE",
                  "members": [
                    {
                      "type": "STRING",
                      "value": "ONLY"
                    },
                    {
                      "type": "STRING",
                      "value": "WRITE"
                    }
                  ]
                }
              ]
            },
            {
              "type": "BLANK"
            }
          ]
        }
      ]
    },
    "commit_stmt": {
      "type": "SEQ",
      "members": [
        {
          "type": "STRING",
          "value": "COMMIT"
        },
        {
          "type": "CHOICE",
          "members": [
            {
              "type": "STRING",
              "value": "TRANSACTION"
            },
            {
              "type": "BLANK"
            }
          ]
        }
      ]
    },
    "select_stmt": {
      "type": "SEQ",
      "members": [
        {
          "type": "STRING",
          "value": "SELECT"
        },
        {
          "type": "CHOICE",
          "members": [
            {
              "type": "STRING",
              "value": "DISTINCT"
            },
            {
              "type": "BLANK"
            }
          ]
        },
        {
          "type": "SYMBOL",
          "name": "projection_exprs"
        },
        {
          "type": "CHOICE",
          "members": [
            {
              "type": "SEQ",
              "members": [
                {
                  "type": "STRING",
                  "value": "FROM"
                },
                {
                  "type": "SYMBOL",
                  "name": "ident"
                },
                {
                  "type": "CHOICE",
                  "members": [
                    {
                      "type": "SEQ",
                      "members": [
                        {
                          "type": "STRING",
                          "value": "WHERE"
                        },
                        {
                          "type": "SYMBOL",
                          "name": "_expr"
                        }
                      ]
                    },
                    {
                      "type": "BLANK"
                    }
                  ]
                },
                {
                  "type": "CHOICE",
                  "members": [
                    {
                      "type": "SEQ",
                      "members": [
                        {
                          "type": "STRING",
                          "value": "GROUP"
                        },
                        {
                          "type": "STRING",
                          "value": "BY"
                        },
                        {
                          "type": "SYMBOL",
                          "name": "_expr"
                        }
                      ]
                    },
                    {
                      "type": "BLANK"
                    }
                  ]
                },
                {
                  "type": "CHOICE",
                  "members": [
                    {
                      "type": "SEQ",
                      "members": [
                        {
                          "type": "STRING",
                          "value": "ORDER"
                        },
                        {
                          "type": "STRING",
                          "value": "BY"
                        },
                        {
                          "type": "CHOICE",
                          "members": [
                            {
                              "type": "STRING",
                              "value": "ASC"
                            },
                            {
                              "type": "STRING",
                              "value": "DESC"
                            }
                          ]
                        }
                      ]
                    },
                    {
                      "type": "BLANK"
                    }
                  ]
                },
                {
                  "type": "CHOICE",
                  "members": [
                    {
                      "type": "SEQ",
                      "members": [
                        {
                          "type": "STRING",
                          "value": "LIMIT"
                        },
                        {
                          "type": "SYMBOL",
                          "name": "_expr"
                        }
                      ]
                    },
                    {
                      "type": "BLANK"
                    }
                  ]
                },
                {
                  "type": "CHOICE",
                  "members": [
                    {
                      "type": "SEQ",
                      "members": [
                        {
                          "type": "STRING",
                          "value": "OFFSET"
                        },
                        {
                          "type": "SYMBOL",
                          "name": "_expr"
                        }
                      ]
                    },
                    {
                      "type": "BLANK"
                    }
                  ]
                },
                {
                  "type": "CHOICE",
                  "members": [
                    {
                      "type": "SEQ",
                      "members": [
                        {
                          "type": "STRING",
                          "value": "UNION"
                        },
                        {
                          "type": "CHOICE",
                          "members": [
                            {
                              "type": "STRING",
                              "value": "ALL"
                            },
                            {
                              "type": "BLANK"
                            }
                          ]
                        },
                        {
                          "type": "SYMBOL",
                          "name": "select_stmt"
                        }
                      ]
                    },
                    {
                      "type": "BLANK"
                    }
                  ]
                }
              ]
            },
            {
              "type": "BLANK"
            }
          ]
        }
      ]
    },
    "delete_stmt": {
      "type": "SEQ",
      "members": [
        {
          "type": "STRING",
          "value": "DELETE"
        },
        {
          "type": "STRING",
          "value": "FROM"
        },
        {
          "type": "SYMBOL",
          "name": "ident"
        },
        {
          "type": "CHOICE",
          "members": [
            {
              "type": "SEQ",
              "members": [
                {
                  "type": "STRING",
                  "value": "WHERE"
                },
                {
                  "type": "SYMBOL",
                  "name": "_expr"
                }
              ]
            },
            {
              "type": "BLANK"
            }
          ]
        },
        {
          "type": "CHOICE",
          "members": [
            {
              "type": "SEQ",
              "members": [
                {
                  "type": "STRING",
                  "value": "ORDER"
                },
                {
                  "type": "STRING",
                  "value": "BY"
                },
                {
                  "type": "CHOICE",
                  "members": [
                    {
                      "type": "STRING",
                      "value": "ASC"
                    },
                    {
                      "type": "STRING",
                      "value": "DESC"
                    }
                  ]
                }
              ]
            },
            {
              "type": "BLANK"
            }
          ]
        },
        {
          "type": "CHOICE",
          "members": [
            {
              "type": "SEQ",
              "members": [
                {
                  "type": "STRING",
                  "value": "LIMIT"
                },
                {
                  "type": "SYMBOL",
                  "name": "_expr"
                }
              ]
            },
            {
              "type": "BLANK"
            }
          ]
        },
        {
          "type": "CHOICE",
          "members": [
            {
              "type": "SEQ",
              "members": [
                {
                  "type": "STRING",
                  "value": "OFFSET"
                },
                {
                  "type": "SYMBOL",
                  "name": "_expr"
                }
              ]
            },
            {
              "type": "BLANK"
            }
          ]
        }
      ]
    },
    "update_stmt": {
      "type": "SEQ",
      "members": [
        {
          "type": "STRING",
          "value": "UPDATE"
        },
        {
          "type": "SYMBOL",
          "name": "ident"
        },
        {
          "type": "CHOICE",
          "members": [
            {
              "type": "SEQ",
              "members": [
                {
                  "type": "STRING",
                  "value": "SET"
                },
                {
                  "type": "REPEAT",
                  "content": {
                    "type": "SEQ",
                    "members": [
                      {
                        "type": "SYMBOL",
                        "name": "path"
                      },
                      {
                        "type": "STRING",
                        "value": "="
                      },
                      {
                        "type": "SYMBOL",
                        "name": "_expr"
                      },
                      {
                        "type": "STRING",
                        "value": ","
                      }
                    ]
                  }
                },
                {
                  "type": "SEQ",
                  "members": [
                    {
                      "type": "SYMBOL",
                      "name": "path"
                    },
                    {
                      "type": "STRING",
                      "value": "="
                    },
                    {
                      "type": "SYMBOL",
                      "name": "_expr"
                    }
                  ]
                }
              ]
            },
            {
              "type": "SEQ",
              "members": [
                {
                  "type": "STRING",
                  "value": "UNSET"
                },
                {
                  "type": "REPEAT",
                  "content": {
                    "type": "SEQ",
                    "members": [
                      {
                        "type": "SYMBOL",
                        "name": "path"
                      },
                      {
                        "type": "STRING",
                        "value": ","
                      }
                    ]
                  }
                },
                {
                  "type": "SYMBOL",
                  "name": "path"
                }
              ]
            }
          ]
        },
        {
          "type": "CHOICE",
          "members": [
            {
              "type": "SEQ",
              "members": [
                {
                  "type": "STRING",
                  "value": "WHERE"
                },
                {
                  "type": "SYMBOL",
                  "name": "_expr"
                }
              ]
            },
            {
              "type": "BLANK"
            }
          ]
        }
      ]
    },
    "insert_stmt": {
      "type": "SEQ",
      "members": [
        {
          "type": "STRING",
          "value": "INSERT"
        },
        {
          "type": "STRING",
          "value": "INTO"
        },
        {
          "type": "SYMBOL",
          "name": "field_list"
        },
        {
          "type": "CHOICE",
          "members": [
            {
              "type": "SEQ",
              "members": [
                {
                  "type": "STRING",
                  "value": "VALUES"
                },
                {
                  "type": "SYMBOL",
                  "name": "values_list"
                }
              ]
            },
            {
              "type": "SYMBOL",
              "name": "select_stmt"
            }
          ]
        },
        {
          "type": "CHOICE",
          "members": [
            {
              "type": "SEQ",
              "members": [
                {
                  "type": "STRING",
                  "value": "RETURNING"
                },
                {
                  "type": "SYMBOL",
                  "name": "projection_exprs"
                }
              ]
            },
            {
              "type": "BLANK"
            }
          ]
        }
      ]
    },
    "create_stmt": {
      "type": "SEQ",
      "members": [
        {
          "type": "STRING",
          "value": "CREATE"
        },
        {
          "type": "CHOICE",
          "members": [
            {
              "type": "SEQ",
              "members": [
                {
                  "type": "STRING",
                  "value": "TABLE"
                }
              ]
            },
            {
              "type": "SEQ",
              "members": [
                {
                  "type": "STRING",
                  "value": "UNIQUE"
                }
              ]
            },
            {
              "type": "SEQ",
              "members": [
                {
                  "type": "STRING",
                  "value": "INDEX"
                }
              ]
            }
          ]
        }
      ]
    },
    "drop_stmt": {
      "type": "SEQ",
      "members": [
        {
          "type": "STRING",
          "value": "DROP"
        },
        {
          "type": "CHOICE",
          "members": [
            {
              "type": "STRING",
              "value": "TABLE"
            },
            {
              "type": "STRING",
              "value": "INDEX"
            }
          ]
        },
        {
          "type": "CHOICE",
          "members": [
            {
              "type": "SEQ",
              "members": [
                {
                  "type": "STRING",
                  "value": "IF"
                },
                {
                  "type": "STRING",
                  "value": "EXISTS"
                }
              ]
            },
            {
              "type": "BLANK"
            }
          ]
        },
        {
          "type": "SYMBOL",
          "name": "ident"
        }
      ]
    },
    "reindex_stmt": {
      "type": "SEQ",
      "members": [
        {
          "type": "STRING",
          "value": "REINDEX"
        },
        {
          "type": "SYMBOL",
          "name": "ident"
        }
      ]
    },
    "rollback_stmt": {
      "type": "SEQ",
      "members": [
        {
          "type": "STRING",
          "value": "ROLLBACK"
        },
        {
          "type": "CHOICE",
          "members": [
            {
              "type": "STRING",
              "value": "TRANSACTION"
            },
            {
              "type": "BLANK"
            }
          ]
        }
      ]
    },
    "ident": {
      "type": "CHOICE",
      "members": [
        {
          "type": "PATTERN",
          "value": "[a-zA-Z]+"
        },
        {
          "type": "SEQ",
          "members": [
            {
              "type": "STRING",
              "value": "`"
            },
            {
              "type": "PATTERN",
              "value": "[^\\n]*"
            },
            {
              "type": "STRING",
              "value": "`"
            }
          ]
        }
      ]
    },
    "number": {
      "type": "CHOICE",
      "members": [
        {
          "type": "SEQ",
          "members": [
            {
              "type": "CHOICE",
              "members": [
                {
                  "type": "SEQ",
                  "members": [
                    {
                      "type": "CHOICE",
                      "members": [
                        {
                          "type": "STRING",
                          "value": "-"
                        },
                        {
                          "type": "BLANK"
                        }
                      ]
                    },
                    {
                      "type": "REPEAT1",
                      "content": {
                        "type": "PATTERN",
                        "value": "[0-9]"
                      }
                    }
                  ]
                },
                {
                  "type": "BLANK"
                }
              ]
            },
            {
              "type": "STRING",
              "value": "."
            },
            {
              "type": "REPEAT1",
              "content": {
                "type": "PATTERN",
                "value": "[0-9]"
              }
            }
          ]
        },
        {
          "type": "SEQ",
          "members": [
            {
              "type": "CHOICE",
              "members": [
                {
                  "type": "STRING",
                  "value": "."
                },
                {
                  "type": "BLANK"
                }
              ]
            },
            {
              "type": "REPEAT1",
              "content": {
                "type": "PATTERN",
                "value": "[0-9]"
              }
            }
          ]
        }
      ]
    },
    "string": {
      "type": "CHOICE",
      "members": [
        {
          "type": "SEQ",
          "members": [
            {
              "type": "STRING",
              "value": "\""
            },
            {
              "type": "PATTERN",
              "value": "[^\\n]*"
            },
            {
              "type": "STRING",
              "value": "\""
            }
          ]
        },
        {
          "type": "SEQ",
          "members": [
            {
              "type": "STRING",
              "value": "'"
            },
            {
              "type": "PATTERN",
              "value": "[^\\n]*"
            },
            {
              "type": "STRING",
              "value": "'"
            }
          ]
        }
      ]
    },
    "bool": {
      "type": "CHOICE",
      "members": [
        {
          "type": "STRING",
          "value": "true"
        },
        {
          "type": "STRING",
          "value": "false"
        }
      ]
    },
    "null": {
      "type": "STRING",
      "value": "NULL"
    },
    "_expr": {
      "type": "CHOICE",
      "members": [
        {
          "type": "SYMBOL",
          "name": "unary_expr"
        },
        {
          "type": "SYMBOL",
          "name": "binary_expr"
        },
        {
          "type": "SYMBOL",
          "name": "number"
        },
        {
          "type": "SYMBOL",
          "name": "string"
        },
        {
          "type": "SYMBOL",
          "name": "bool"
        },
        {
          "type": "SYMBOL",
          "name": "null"
        },
        {
          "type": "SYMBOL",
          "name": "ident"
        },
        {
          "type": "SYMBOL",
          "name": "document"
        },
        {
          "type": "SYMBOL",
          "name": "array"
        }
      ]
    },
    "unary_expr": {
      "type": "CHOICE",
      "members": [
        {
          "type": "PREC_LEFT",
          "value": "unary_not",
          "content": {
            "type": "SEQ",
            "members": [
              {
                "type": "FIELD",
                "name": "operator",
                "content": {
                  "type": "STRING",
                  "value": "NOT"
                }
              },
              {
                "type": "FIELD",
                "name": "argument",
                "content": {
                  "type": "SYMBOL",
                  "name": "_expr"
                }
              }
            ]
          }
        }
      ]
    },
    "cast_expr": {
      "type": "SEQ",
      "members": [
        {
          "type": "STRING",
          "value": "CAST"
        },
        {
          "type": "STRING",
          "value": "("
        },
        {
          "type": "SYMBOL",
          "name": "_expr"
        },
        {
          "type": "STRING",
          "value": "AS"
        },
        {
          "type": "CHOICE",
          "members": [
            {
              "type": "STRING",
              "value": "ARRAY"
            },
            {
              "type": "STRING",
              "value": "BIGINT"
            },
            {
              "type": "STRING",
              "value": "BLOB"
            },
            {
              "type": "STRING",
              "value": "BOOL"
            },
            {
              "type": "STRING",
              "value": "BYTES"
            },
            {
              "type": "STRING",
              "value": "CHARACTER"
            },
            {
              "type": "STRING",
              "value": "DOCUMENT"
            },
            {
              "type": "SEQ",
              "members": [
                {
                  "type": "STRING",
                  "value": "DOUBLE"
                },
                {
                  "type": "CHOICE",
                  "members": [
                    {
                      "type": "STRING",
                      "value": "PRECISION"
                    },
                    {
                      "type": "BLANK"
                    }
                  ]
                }
              ]
            },
            {
              "type": "STRING",
              "value": "INT"
            },
            {
              "type": "STRING",
              "value": "INT2"
            },
            {
              "type": "STRING",
              "value": "INT8"
            },
            {
              "type": "STRING",
              "value": "INTEGER"
            },
            {
              "type": "STRING",
              "value": "MEDIUMINT"
            },
            {
              "type": "STRING",
              "value": "SMALLINT"
            },
            {
              "type": "STRING",
              "value": "TEXT"
            },
            {
              "type": "STRING",
              "value": "TINYINT"
            },
            {
              "type": "STRING",
              "value": "REAL"
            },
            {
              "type": "SEQ",
              "members": [
                {
                  "type": "STRING",
                  "value": "VARCHAR"
                },
                {
                  "type": "CHOICE",
                  "members": [
                    {
                      "type": "SEQ",
                      "members": [
                        {
                          "type": "STRING",
                          "value": "("
                        },
                        {
                          "type": "PATTERN",
                          "value": "\\d+"
                        },
                        {
                          "type": "STRING",
                          "value": ")"
                        }
                      ]
                    },
                    {
                      "type": "BLANK"
                    }
                  ]
                }
              ]
            }
          ]
        },
        {
          "type": "STRING",
          "value": ")"
        }
      ]
    },
    "func_expr": {
      "type": "CHOICE",
      "members": [
        {
          "type": "SEQ",
          "members": [
            {
              "type": "STRING",
              "value": "COUNT"
            },
            {
              "type": "STRING",
              "value": "("
            },
            {
              "type": "STRING",
              "value": "*"
            },
            {
              "type": "STRING",
              "value": ")"
            }
          ]
        },
        {
          "type": "SEQ",
          "members": [
            {
              "type": "SYMBOL",
              "name": "ident"
            },
            {
              "type": "CHOICE",
              "members": [
                {
                  "type": "SEQ",
                  "members": [
                    {
                      "type": "STRING",
                      "value": "("
                    },
                    {
                      "type": "STRING",
                      "value": ")"
                    }
                  ]
                },
                {
                  "type": "SEQ",
                  "members": [
                    {
                      "type": "STRING",
                      "value": "("
                    },
                    {
                      "type": "REPEAT",
                      "content": {
                        "type": "SEQ",
                        "members": [
                          {
                            "type": "SYMBOL",
                            "name": "_expr"
                          },
                          {
                            "type": "STRING",
                            "value": ","
                          }
                        ]
                      }
                    },
                    {
                      "type": "SYMBOL",
                      "name": "_expr"
                    },
                    {
                      "type": "STRING",
                      "value": ")"
                    }
                  ]
                }
              ]
            }
          ]
        }
      ]
    },
    "projection_exprs": {
      "type": "CHOICE",
      "members": [
        {
          "type": "STRING",
          "value": "*"
        },
        {
          "type": "SEQ",
          "members": [
            {
              "type": "SYMBOL",
              "name": "_expr"
            },
            {
              "type": "CHOICE",
              "members": [
                {
                  "type": "SEQ",
                  "members": [
                    {
                      "type": "STRING",
                      "value": "AS"
                    },
                    {
                      "type": "SYMBOL",
                      "name": "ident"
                    }
                  ]
                },
                {
                  "type": "BLANK"
                }
              ]
            }
          ]
        }
      ]
    },
    "values_list": {
      "type": "CHOICE",
      "members": [
        {
          "type": "SEQ",
          "members": [
            {
              "type": "STRING",
              "value": "("
            },
            {
              "type": "REPEAT",
              "content": {
                "type": "SEQ",
                "members": [
                  {
                    "type": "SYMBOL",
                    "name": "_expr"
                  },
                  {
                    "type": "STRING",
                    "value": ","
                  }
                ]
              }
            },
            {
              "type": "SYMBOL",
              "name": "_expr"
            },
            {
              "type": "STRING",
              "value": ")"
            }
          ]
        },
        {
          "type": "SEQ",
          "members": [
            {
              "type": "CHOICE",
              "members": [
                {
                  "type": "SYMBOL",
                  "name": "named_param"
                },
                {
                  "type": "SYMBOL",
                  "name": "positional_param"
                }
              ]
            }
          ]
        },
        {
          "type": "SYMBOL",
          "name": "document"
        }
      ]
    },
    "field_list": {
      "type": "SEQ",
      "members": [
        {
          "type": "STRING",
          "value": "("
        },
        {
          "type": "REPEAT",
          "content": {
            "type": "SEQ",
            "members": [
              {
                "type": "SYMBOL",
                "name": "ident"
              },
              {
                "type": "STRING",
                "value": ","
              }
            ]
          }
        },
        {
          "type": "SYMBOL",
          "name": "ident"
        },
        {
          "type": "STRING",
          "value": ")"
        }
      ]
    },
    "binary_expr": {
      "type": "CHOICE",
      "members": [
        {
          "type": "PREC_LEFT",
          "value": "binary_and",
          "content": {
            "type": "SEQ",
            "members": [
              {
                "type": "FIELD",
                "name": "left",
                "content": {
                  "type": "SYMBOL",
                  "name": "_expr"
                }
              },
              {
                "type": "FIELD",
                "name": "operator",
                "content": {
                  "type": "STRING",
                  "value": "&&"
                }
              },
              {
                "type": "FIELD",
                "name": "right",
                "content": {
                  "type": "SYMBOL",
                  "name": "_expr"
                }
              }
            ]
          }
        },
        {
          "type": "PREC_LEFT",
          "value": "binary_or",
          "content": {
            "type": "SEQ",
            "members": [
              {
                "type": "FIELD",
                "name": "left",
                "content": {
                  "type": "SYMBOL",
                  "name": "_expr"
                }
              },
              {
                "type": "FIELD",
                "name": "operator",
                "content": {
                  "type": "STRING",
                  "value": "||"
                }
              },
              {
                "type": "FIELD",
                "name": "right",
                "content": {
                  "type": "SYMBOL",
                  "name": "_expr"
                }
              }
            ]
          }
        },
        {
          "type": "PREC_LEFT",
          "value": "binary_and",
          "content": {
            "type": "SEQ",
            "members": [
              {
                "type": "FIELD",
                "name": "left",
                "content": {
                  "type": "SYMBOL",
                  "name": "_expr"
                }
              },
              {
                "type": "FIELD",
                "name": "operator",
                "content": {
                  "type": "STRING",
                  "value": "&"
                }
              },
              {
                "type": "FIELD",
                "name": "right",
                "content": {
                  "type": "SYMBOL",
                  "name": "_expr"
                }
              }
            ]
          }
        },
        {
          "type": "PREC_LEFT",
          "value": "binary_or",
          "content": {
            "type": "SEQ",
            "members": [
              {
                "type": "FIELD",
                "name": "left",
                "content": {
                  "type": "SYMBOL",
                  "name": "_expr"
                }
              },
              {
                "type": "FIELD",
                "name": "operator",
                "content": {
                  "type": "STRING",
                  "value": "^"
                }
              },
              {
                "type": "FIELD",
                "name": "right",
                "content": {
                  "type": "SYMBOL",
                  "name": "_expr"
                }
              }
            ]
          }
        },
        {
          "type": "PREC_LEFT",
          "value": "binary_or",
          "content": {
            "type": "SEQ",
            "members": [
              {
                "type": "FIELD",
                "name": "left",
                "content": {
                  "type": "SYMBOL",
                  "name": "_expr"
                }
              },
              {
                "type": "FIELD",
                "name": "operator",
                "content": {
                  "type": "STRING",
                  "value": "|"
                }
              },
              {
                "type": "FIELD",
                "name": "right",
                "content": {
                  "type": "SYMBOL",
                  "name": "_expr"
                }
              }
            ]
          }
        },
        {
          "type": "PREC_LEFT",
          "value": "binary_plus",
          "content": {
            "type": "SEQ",
            "members": [
              {
                "type": "FIELD",
                "name": "left",
                "content": {
                  "type": "SYMBOL",
                  "name": "_expr"
                }
              },
              {
                "type": "FIELD",
                "name": "operator",
                "content": {
                  "type": "STRING",
                  "value": "+"
                }
              },
              {
                "type": "FIELD",
                "name": "right",
                "content": {
                  "type": "SYMBOL",
                  "name": "_expr"
                }
              }
            ]
          }
        },
        {
          "type": "PREC_LEFT",
          "value": "binary_plus",
          "content": {
            "type": "SEQ",
            "members": [
              {
                "type": "FIELD",
                "name": "left",
                "content": {
                  "type": "SYMBOL",
                  "name": "_expr"
                }
              },
              {
                "type": "FIELD",
                "name": "operator",
                "content": {
                  "type": "STRING",
                  "value": "-"
                }
              },
              {
                "type": "FIELD",
                "name": "right",
                "content": {
                  "type": "SYMBOL",
                  "name": "_expr"
                }
              }
            ]
          }
        },
        {
          "type": "PREC_LEFT",
          "value": "binary_times",
          "content": {
            "type": "SEQ",
            "members": [
              {
                "type": "FIELD",
                "name": "left",
                "content": {
                  "type": "SYMBOL",
                  "name": "_expr"
                }
              },
              {
                "type": "FIELD",
                "name": "operator",
                "content": {
                  "type": "STRING",
                  "value": "*"
                }
              },
              {
                "type": "FIELD",
                "name": "right",
                "content": {
                  "type": "SYMBOL",
                  "name": "_expr"
                }
              }
            ]
          }
        },
        {
          "type": "PREC_LEFT",
          "value": "binary_times",
          "content": {
            "type": "SEQ",
            "members": [
              {
                "type": "FIELD",
                "name": "left",
                "content": {
                  "type": "SYMBOL",
                  "name": "_expr"
                }
              },
              {
                "type": "FIELD",
                "name": "operator",
                "content": {
                  "type": "STRING",
                  "value": "/"
                }
              },
              {
                "type": "FIELD",
                "name": "right",
                "content": {
                  "type": "SYMBOL",
                  "name": "_expr"
                }
              }
            ]
          }
        },
        {
          "type": "PREC_LEFT",
          "value": "binary_times",
          "content": {
            "type": "SEQ",
            "members": [
              {
                "type": "FIELD",
                "name": "left",
                "content": {
                  "type": "SYMBOL",
                  "name": "_expr"
                }
              },
              {
                "type": "FIELD",
                "name": "operator",
                "content": {
                  "type": "STRING",
                  "value": "%"
                }
              },
              {
                "type": "FIELD",
                "name": "right",
                "content": {
                  "type": "SYMBOL",
                  "name": "_expr"
                }
              }
            ]
          }
        },
        {
          "type": "PREC_LEFT",
          "value": "binary_relation",
          "content": {
            "type": "SEQ",
            "members": [
              {
                "type": "FIELD",
                "name": "left",
                "content": {
                  "type": "SYMBOL",
                  "name": "_expr"
                }
              },
              {
                "type": "FIELD",
                "name": "operator",
                "content": {
                  "type": "STRING",
                  "value": "<"
                }
              },
              {
                "type": "FIELD",
                "name": "right",
                "content": {
                  "type": "SYMBOL",
                  "name": "_expr"
                }
              }
            ]
          }
        },
        {
          "type": "PREC_LEFT",
          "value": "binary_relation",
          "content": {
            "type": "SEQ",
            "members": [
              {
                "type": "FIELD",
                "name": "left",
                "content": {
                  "type": "SYMBOL",
                  "name": "_expr"
                }
              },
              {
                "type": "FIELD",
                "name": "operator",
                "content": {
                  "type": "STRING",
                  "value": "<="
                }
              },
              {
                "type": "FIELD",
                "name": "right",
                "content": {
                  "type": "SYMBOL",
                  "name": "_expr"
                }
              }
            ]
          }
        },
        {
          "type": "PREC_LEFT",
          "value": "binary_relation",
          "content": {
            "type": "SEQ",
            "members": [
              {
                "type": "FIELD",
                "name": "left",
                "content": {
                  "type": "SYMBOL",
                  "name": "_expr"
                }
              },
              {
                "type": "FIELD",
                "name": "operator",
                "content": {
                  "type": "STRING",
                  "value": "="
                }
              },
              {
                "type": "FIELD",
                "name": "right",
                "content": {
                  "type": "SYMBOL",
                  "name": "_expr"
                }
              }
            ]
          }
        },
        {
          "type": "PREC_LEFT",
          "value": "binary_relation",
          "content": {
            "type": "SEQ",
            "members": [
              {
                "type": "FIELD",
                "name": "left",
                "content": {
                  "type": "SYMBOL",
                  "name": "_expr"
                }
              },
              {
                "type": "FIELD",
                "name": "operator",
                "content": {
                  "type": "STRING",
                  "value": "!="
                }
              },
              {
                "type": "FIELD",
                "name": "right",
                "content": {
                  "type": "SYMBOL",
                  "name": "_expr"
                }
              }
            ]
          }
        },
        {
          "type": "PREC_LEFT",
          "value": "binary_relation",
          "content": {
            "type": "SEQ",
            "members": [
              {
                "type": "FIELD",
                "name": "left",
                "content": {
                  "type": "SYMBOL",
                  "name": "_expr"
                }
              },
              {
                "type": "FIELD",
                "name": "operator",
                "content": {
                  "type": "STRING",
                  "value": ">="
                }
              },
              {
                "type": "FIELD",
                "name": "right",
                "content": {
                  "type": "SYMBOL",
                  "name": "_expr"
                }
              }
            ]
          }
        },
        {
          "type": "PREC_LEFT",
          "value": "binary_relation",
          "content": {
            "type": "SEQ",
            "members": [
              {
                "type": "FIELD",
                "name": "left",
                "content": {
                  "type": "SYMBOL",
                  "name": "_expr"
                }
              },
              {
                "type": "FIELD",
                "name": "operator",
                "content": {
                  "type": "STRING",
                  "value": ">"
                }
              },
              {
                "type": "FIELD",
                "name": "right",
                "content": {
                  "type": "SYMBOL",
                  "name": "_expr"
                }
              }
            ]
          }
        },
        {
          "type": "PREC_LEFT",
          "value": "binary_relation",
          "content": {
            "type": "SEQ",
            "members": [
              {
                "type": "FIELD",
                "name": "left",
                "content": {
                  "type": "SYMBOL",
                  "name": "_expr"
                }
              },
              {
                "type": "FIELD",
                "name": "operator",
                "content": {
                  "type": "STRING",
                  "value": "CONCAT"
                }
              },
              {
                "type": "FIELD",
                "name": "right",
                "content": {
                  "type": "SYMBOL",
                  "name": "_expr"
                }
              }
            ]
          }
        },
        {
          "type": "PREC_LEFT",
          "value": "binary_relation",
          "content": {
            "type": "SEQ",
            "members": [
              {
                "type": "FIELD",
                "name": "left",
                "content": {
                  "type": "SYMBOL",
                  "name": "_expr"
                }
              },
              {
                "type": "FIELD",
                "name": "operator",
                "content": {
                  "type": "STRING",
                  "value": "LIKE"
                }
              },
              {
                "type": "FIELD",
                "name": "right",
                "content": {
                  "type": "SYMBOL",
                  "name": "_expr"
                }
              }
            ]
          }
        },
        {
          "type": "PREC_LEFT",
          "value": "binary_relation",
          "content": {
            "type": "SEQ",
            "members": [
              {
                "type": "FIELD",
                "name": "left",
                "content": {
                  "type": "SYMBOL",
                  "name": "_expr"
                }
              },
              {
                "type": "FIELD",
                "name": "operator",
                "content": {
                  "type": "SEQ",
                  "members": [
                    {
                      "type": "STRING",
                      "value": "NOT"
                    },
                    {
                      "type": "STRING",
                      "value": "LIKE"
                    }
                  ]
                }
              },
              {
                "type": "FIELD",
                "name": "right",
                "content": {
                  "type": "SYMBOL",
                  "name": "_expr"
                }
              }
            ]
          }
        },
        {
          "type": "PREC_LEFT",
          "value": "binary_relation",
          "content": {
            "type": "SEQ",
            "members": [
              {
                "type": "FIELD",
                "name": "left",
                "content": {
                  "type": "SYMBOL",
                  "name": "_expr"
                }
              },
              {
                "type": "FIELD",
                "name": "operator",
                "content": {
                  "type": "STRING",
                  "value": "IS"
                }
              },
              {
                "type": "FIELD",
                "name": "right",
                "content": {
                  "type": "SYMBOL",
                  "name": "_expr"
                }
              }
            ]
          }
        },
        {
          "type": "PREC_LEFT",
          "value": "binary_relation",
          "content": {
            "type": "SEQ",
            "members": [
              {
                "type": "FIELD",
                "name": "left",
                "content": {
                  "type": "SYMBOL",
                  "name": "_expr"
                }
              },
              {
                "type": "FIELD",
                "name": "operator",
                "content": {
                  "type": "STRING",
                  "value": "IN"
                }
              },
              {
                "type": "FIELD",
                "name": "right",
                "content": {
                  "type": "SYMBOL",
                  "name": "_expr"
                }
              }
            ]
          }
        },
        {
          "type": "PREC_LEFT",
          "value": "binary_relation",
          "content": {
            "type": "SEQ",
            "members": [
              {
                "type": "FIELD",
                "name": "left",
                "content": {
                  "type": "SYMBOL",
                  "name": "_expr"
                }
              },
              {
                "type": "FIELD",
                "name": "operator",
                "content": {
                  "type": "SEQ",
                  "members": [
                    {
                      "type": "STRING",
                      "value": "NOT"
                    },
                    {
                      "type": "STRING",
                      "value": "IN"
                    }
                  ]
                }
              },
              {
                "type": "FIELD",
                "name": "right",
                "content": {
                  "type": "SYMBOL",
                  "name": "_expr"
                }
              }
            ]
          }
        },
        {
          "type": "PREC_LEFT",
          "value": "binary_relation",
          "content": {
            "type": "SEQ",
            "members": [
              {
                "type": "FIELD",
                "name": "left",
                "content": {
                  "type": "SYMBOL",
                  "name": "_expr"
                }
              },
              {
                "type": "FIELD",
                "name": "operator",
                "content": {
                  "type": "SEQ",
                  "members": [
                    {
                      "type": "STRING",
                      "value": "IS"
                    },
                    {
                      "type": "STRING",
                      "value": "NOT"
                    }
                  ]
                }
              },
              {
                "type": "FIELD",
                "name": "right",
                "content": {
                  "type": "SYMBOL",
                  "name": "_expr"
                }
              }
            ]
          }
        }
      ]
    },
    "document": {
      "type": "CHOICE",
      "members": [
        {
          "type": "SEQ",
          "members": [
            {
              "type": "STRING",
              "value": "{"
            },
            {
              "type": "STRING",
              "value": "}"
            }
          ]
        },
        {
          "type": "SEQ",
          "members": [
            {
              "type": "STRING",
              "value": "{"
            },
            {
              "type": "REPEAT",
              "content": {
                "type": "SEQ",
                "members": [
                  {
                    "type": "SYMBOL",
                    "name": "kv_pair"
                  },
                  {
                    "type": "STRING",
                    "value": ","
                  }
                ]
              }
            },
            {
              "type": "SYMBOL",
              "name": "kv_pair"
            },
            {
              "type": "STRING",
              "value": "}"
            }
          ]
        }
      ]
    },
    "kv_pair": {
      "type": "SEQ",
      "members": [
        {
          "type": "CHOICE",
          "members": [
            {
              "type": "CHOICE",
              "members": [
                {
                  "type": "SEQ",
                  "members": [
                    {
                      "type": "STRING",
                      "value": "\""
                    },
                    {
                      "type": "PATTERN",
                      "value": "[^\\n]*"
                    },
                    {
                      "type": "STRING",
                      "value": "\""
                    }
                  ]
                },
                {
                  "type": "SEQ",
                  "members": [
                    {
                      "type": "STRING",
                      "value": "'"
                    },
                    {
                      "type": "PATTERN",
                      "value": "[^\\n]*"
                    },
                    {
                      "type": "STRING",
                      "value": "'"
                    }
                  ]
                }
              ]
            },
            {
              "type": "SYMBOL",
              "name": "ident"
            }
          ]
        },
        {
          "type": "STRING",
          "value": ":"
        },
        {
          "type": "SYMBOL",
          "name": "_expr"
        }
      ]
    },
    "array": {
      "type": "CHOICE",
      "members": [
        {
          "type": "SEQ",
          "members": [
            {
              "type": "STRING",
              "value": "["
            },
            {
              "type": "STRING",
              "value": "]"
            }
          ]
        },
        {
          "type": "SEQ",
          "members": [
            {
              "type": "STRING",
              "value": "["
            },
            {
              "type": "REPEAT",
              "content": {
                "type": "SEQ",
                "members": [
                  {
                    "type": "SYMBOL",
                    "name": "_expr"
                  },
                  {
                    "type": "STRING",
                    "value": ","
                  }
                ]
              }
            },
            {
              "type": "SYMBOL",
              "name": "_expr"
            },
            {
              "type": "STRING",
              "value": "]"
            }
          ]
        }
      ]
    },
    "path": {
      "type": "SEQ",
      "members": [
        {
          "type": "SYMBOL",
          "name": "ident"
        },
        {
          "type": "REPEAT",
          "content": {
            "type": "CHOICE",
            "members": [
              {
                "type": "SEQ",
                "members": [
                  {
                    "type": "STRING",
                    "value": "["
                  },
                  {
                    "type": "PATTERN",
                    "value": "\\d+"
                  },
                  {
                    "type": "STRING",
                    "value": "]"
                  }
                ]
              },
              {
                "type": "SEQ",
                "members": [
                  {
                    "type": "STRING",
                    "value": "."
                  },
                  {
                    "type": "SYMBOL",
                    "name": "ident"
                  }
                ]
              }
            ]
          }
        }
      ]
    },
    "named_param": {
      "type": "SEQ",
      "members": [
        {
          "type": "STRING",
          "value": "$"
        },
        {
          "type": "SYMBOL",
          "name": "ident"
        }
      ]
    },
    "positional_param": {
      "type": "STRING",
      "value": "?"
    },
    "comment": {
      "type": "TOKEN",
      "content": {
        "type": "CHOICE",
        "members": [
          {
            "type": "SEQ",
            "members": [
              {
                "type": "STRING",
                "value": "--"
              },
              {
                "type": "PATTERN",
                "value": ".*"
              }
            ]
          },
          {
            "type": "SEQ",
            "members": [
              {
                "type": "STRING",
                "value": "/*"
              },
              {
                "type": "PATTERN",
                "value": "[^*]*\\*+([^/*][^*]*\\*+)*"
              },
              {
                "type": "STRING",
                "value": "/"
              }
            ]
          }
        ]
      }
    },
    "regex_pattern": {
      "type": "IMMEDIATE_TOKEN",
      "content": {
        "type": "PREC",
        "value": -1,
        "content": {
          "type": "REPEAT1",
          "content": {
            "type": "CHOICE",
            "members": [
              {
                "type": "SEQ",
                "members": [
                  {
                    "type": "STRING",
                    "value": "["
                  },
                  {
                    "type": "REPEAT",
                    "content": {
                      "type": "CHOICE",
                      "members": [
                        {
                          "type": "SEQ",
                          "members": [
                            {
                              "type": "STRING",
                              "value": "\\"
                            },
                            {
                              "type": "PATTERN",
                              "value": "."
                            }
                          ]
                        },
                        {
                          "type": "PATTERN",
                          "value": "[^\\]\\n\\\\]"
                        }
                      ]
                    }
                  },
                  {
                    "type": "STRING",
                    "value": "]"
                  }
                ]
              },
              {
                "type": "SEQ",
                "members": [
                  {
                    "type": "STRING",
                    "value": "\\"
                  },
                  {
                    "type": "PATTERN",
                    "value": "."
                  }
                ]
              },
              {
                "type": "PATTERN",
                "value": "[^/\\\\\\[\\n]"
              }
            ]
          }
        }
      }
    },
    "regex": {
      "type": "SEQ",
      "members": [
        {
          "type": "STRING",
          "value": "/"
        },
        {
          "type": "FIELD",
          "name": "pattern",
          "content": {
            "type": "SYMBOL",
            "name": "regex_pattern"
          }
        },
        {
          "type": "IMMEDIATE_TOKEN",
          "content": {
            "type": "STRING",
            "value": "/"
          }
        }
      ]
    }
  },
  "extras": [
    {
      "type": "PATTERN",
      "value": "\\s"
    }
  ],
  "conflicts": [],
  "precedences": [
    [
      {
        "type": "STRING",
        "value": "unary_not"
      },
      {
        "type": "STRING",
        "value": "binary_times"
      },
      {
        "type": "STRING",
        "value": "binary_plus"
      },
      {
        "type": "STRING",
        "value": "binary_relation"
      },
      {
        "type": "STRING",
        "value": "binary_and"
      },
      {
        "type": "STRING",
        "value": "binary_or"
      }
    ]
  ],
  "externals": [],
  "inline": [],
  "supertypes": []
}

